[
    {
        "id": 1,
        "username": "AmparoHaagDVM",
        "nombre_apellidos": "Prof. Amelie Rogahn",
        "direccion": "2735 Daniel Fall Suite 050\nProhaskafurt, ND 22498",
        "telefono": "+17813899794",
        "email": "celine.bashirian@example.net",
        "email_registro": "aurelia.gislason@example.net",
        "cubano": false,
        "numero_tramite": 1087,
        "observaciones": "Mollitia saepe dignissimos consequatur ut.",
        "monto_pagar": 8702,
        "monto_pago": 6929,
        "tipo_tramite": "matrimonio",
        "fecha": "1990-03-23",
        "created_at": "2024-06-14T00:30:43.000000Z",
        "updated_at": "2024-06-14T00:30:43.000000Z"
    },
    {
        "id": 2,
        "username": "Prof.RoderickHills",
        "nombre_apellidos": "Alexandrea Graham",
        "direccion": "1067 Aron Plains Apt. 023\nEdmondstad, IA 56980",
        "telefono": "919.305.1149",
        "email": "mckenzie.dayne@example.com",
        "email_registro": "leif.yundt@example.org",
        "cubano": false,
        "numero_tramite": 1087,
        "observaciones": "Mollitia saepe dignissimos consequatur ut.",
        "monto_pagar": 8702,
        "monto_pago": 6929,
        "tipo_tramite": "matrimonio",
        "fecha": "1990-03-23",
        "created_at": "2024-06-14T00:30:43.000000Z",
        "updated_at": "2024-06-14T00:30:43.000000Z"
    },
    {
        "id": 3,
        "username": "JacintheHyatt",
        "nombre_apellidos": "Tabitha Kiehn",
        "direccion": "78807 Karianne Freeway\nLake Hilbert, SD 05704",
        "telefono": "+1 (678) 453-6866",
        "email": "wconn@example.net",
        "email_registro": "gulgowski.gust@example.net",
        "cubano": true,
        "numero_tramite": 7484,
        "observaciones": "Distinctio aut eos sed.",
        "monto_pagar": 4368,
        "monto_pago": 3518,
        "tipo_tramite": "matrimonio",
        "fecha": "1983-02-27",
        "created_at": "2024-06-14T00:30:44.000000Z",
        "updated_at": "2024-06-14T00:30:44.000000Z"
    },
    {
        "id": 4,
        "username": "DesmondBlick",
        "nombre_apellidos": "Mr. Cade Schroeder DVM",
        "direccion": "59777 Julianne Port Suite 905\nEast Lilian, MT 18994",
        "telefono": "847-474-1011",
        "email": "jaylan.boehm@example.com",
        "email_registro": "jamie.shanahan@example.org",
        "cubano": false,
        "numero_tramite": 7484,
        "observaciones": "Distinctio aut eos sed.",
        "monto_pagar": 4368,
        "monto_pago": 3518,
        "tipo_tramite": "matrimonio",
        "fecha": "1983-02-27",
        "created_at": "2024-06-14T00:30:44.000000Z",
        "updated_at": "2024-06-14T00:30:44.000000Z"
    },
    {
        "id": 5,
        "username": "AdriannaO'Connell",
        "nombre_apellidos": "Jedediah Heller IV",
        "direccion": "3595 Marvin Unions\nNew Savanahport, KS 78062",
        "telefono": "229.293.5262",
        "email": "qchamplin@example.com",
        "email_registro": "barry.rodriguez@example.org",
        "cubano": true,
        "numero_tramite": 9043,
        "observaciones": "Doloremque et distinctio et dolorum.",
        "monto_pagar": 9166,
        "monto_pago": 6918,
        "tipo_tramite": "matrimonio",
        "fecha": "2008-06-13",
        "created_at": "2024-06-14T00:30:44.000000Z",
        "updated_at": "2024-06-14T00:30:44.000000Z"
    },
    {
        "id": 6,
        "username": "ManleyKuhlman",
        "nombre_apellidos": "Peyton Spinka Jr.",
        "direccion": "645 Cheyenne Ramp Apt. 362\nEast Fredashire, GA 05285",
        "telefono": "+1-985-287-5485",
        "email": "ipredovic@example.net",
        "email_registro": "obuckridge@example.net",
        "cubano": true,
        "numero_tramite": 9043,
        "observaciones": "Doloremque et distinctio et dolorum.",
        "monto_pagar": 9166,
        "monto_pago": 6918,
        "tipo_tramite": "matrimonio",
        "fecha": "2008-06-13",
        "created_at": "2024-06-14T00:30:44.000000Z",
        "updated_at": "2024-06-14T00:30:44.000000Z"
    },
    {
        "id": 7,
        "username": "Dr.WillardBeierIV",
        "nombre_apellidos": "Earnest Trantow",
        "direccion": "669 Gibson Route Suite 566\nWest Williamton, MD 21972",
        "telefono": "332.215.6045",
        "email": "monahan.laurine@example.com",
        "email_registro": "mlegros@example.net",
        "cubano": true,
        "numero_tramite": 4420,
        "observaciones": "Dicta porro nisi est corporis velit rerum.",
        "monto_pagar": 5116,
        "monto_pago": 200,
        "tipo_tramite": "matrimonio",
        "fecha": "1988-12-16",
        "created_at": "2024-06-14T00:30:45.000000Z",
        "updated_at": "2024-06-14T00:30:45.000000Z"
    },
    {
        "id": 8,
        "username": "AbelardoBatz",
        "nombre_apellidos": "Cleora Bergnaum",
        "direccion": "94730 Ruecker Bridge Suite 727\nPort Jewell, AZ 85789-5951",
        "telefono": "+13179350328",
        "email": "oabshire@example.net",
        "email_registro": "wdaugherty@example.com",
        "cubano": true,
        "numero_tramite": 4420,
        "observaciones": "Dicta porro nisi est corporis velit rerum.",
        "monto_pagar": 5116,
        "monto_pago": 200,
        "tipo_tramite": "matrimonio",
        "fecha": "1988-12-16",
        "created_at": "2024-06-14T00:30:45.000000Z",
        "updated_at": "2024-06-14T00:30:45.000000Z"
    },
    {
        "id": 9,
        "username": "LilianeBrakus",
        "nombre_apellidos": "Markus Runte",
        "direccion": "648 Hand Glen Suite 064\nBeahanmouth, CA 51439",
        "telefono": "+1-413-873-4310",
        "email": "keshawn72@example.com",
        "email_registro": "stanton.bailey@example.org",
        "cubano": false,
        "numero_tramite": 7725,
        "observaciones": "Quo iure voluptatem unde quae ducimus doloremque.",
        "monto_pagar": 337,
        "monto_pago": 9778,
        "tipo_tramite": "matrimonio",
        "fecha": "2009-12-10",
        "created_at": "2024-06-14T00:30:45.000000Z",
        "updated_at": "2024-06-14T00:30:45.000000Z"
    },
    {
        "id": 10,
        "username": "MuhammadVolkman",
        "nombre_apellidos": "Modesto Torphy",
        "direccion": "316 Maximillian Hills Suite 641\nPrincessmouth, DC 65805-6143",
        "telefono": "+17408872371",
        "email": "cierra38@example.com",
        "email_registro": "lakin.lillie@example.org",
        "cubano": false,
        "numero_tramite": 7725,
        "observaciones": "Quo iure voluptatem unde quae ducimus doloremque.",
        "monto_pagar": 337,
        "monto_pago": 9778,
        "tipo_tramite": "matrimonio",
        "fecha": "2009-12-10",
        "created_at": "2024-06-14T00:30:45.000000Z",
        "updated_at": "2024-06-14T00:30:45.000000Z"
    }
]